tube_dl/__init__.py
tube_dl/__main__.py
tube_dl/captions.py
tube_dl/comments.py
tube_dl/decipher.py
tube_dl/extras.py
tube_dl/formats.py
tube_dl/tdexceptions.py
tube_dl-5.1.0.dist-info/LICENSE
tube_dl-5.1.0.dist-info/METADATA
tube_dl-5.1.0.dist-info/WHEEL
tube_dl-5.1.0.dist-info/top_level.txt
tube_dl-5.1.0.dist-info/RECORD
