Metadata-Version: 2.1
Name: tube-dl
Version: 5.1.0
Summary: Another Youtube Video Downloader for Python.
Home-page: https://github.com/shekharchander/tube_dl
Author: Shekhar Chander
Author-email: shekhar1000.sc@gmail.com
License: UNKNOWN
Platform: UNKNOWN
Classifier: Programming Language :: Python :: 3
Classifier: License :: OSI Approved :: MIT License
Classifier: Operating System :: OS Independent
Requires-Python: >=3.6
